fldr/__init__.py
fldr/fldr.py
fldr/fldrf.py
fldr/tests/__init__.py
fldr/tests/test_fldr.py
fldr/tests/test_fldrf.py
fldr-1.4.8.dist-info/licenses/LICENSE.txt
fldr-1.4.8.dist-info/METADATA
fldr-1.4.8.dist-info/WHEEL
fldr-1.4.8.dist-info/top_level.txt
fldr-1.4.8.dist-info/RECORD
