Metadata-Version: 2.4
Name: fldr
Version: 1.4.8
Summary: Fast Loaded Dice Roller
Home-page: https://github.com/probcomp/fast-loaded-dice-roller
Maintainer: Feras A. Saad
Maintainer-email: fsaad@mit.edu
License: Apache-2.0
Classifier: Development Status :: 2 - Pre-Alpha
Classifier: Intended Audience :: Science/Research
Classifier: License :: OSI Approved :: Apache Software License
Classifier: Programming Language :: Python :: 3
License-File: LICENSE.txt
Provides-Extra: tests
Requires-Dist: pytest; extra == "tests"
Requires-Dist: flaky; extra == "tests"
Requires-Dist: scipy; extra == "tests"
Dynamic: classifier
Dynamic: description
Dynamic: description-content-type
Dynamic: home-page
Dynamic: license
Dynamic: license-file
Dynamic: maintainer
Dynamic: maintainer-email
Dynamic: provides-extra
Dynamic: summary
